tyuio
