Metadata-Version: 1.1
Name: tyuio
Version: 0.4
Summary: Tyuio is a Simple Event Dispatcher api.
Home-page: https://github.com/moisespsena/py_tyuio
Author: Moises P. Sena
Author-email: moisespsena@gmail.com
License: GPLv2
Keywords: event dispatcher
Platform: UNKNOWN
Classifier: Development Status :: 4 - Beta
Classifier: Topic :: Utilities
Classifier: Intended Audience :: Developers
Classifier: License :: OSI Approved :: GNU General Public License v2 (GPLv2)
Classifier: Operating System :: OS Independent
Classifier: Programming Language :: Python :: 2
Classifier: Programming Language :: Python :: 2.7
Classifier: Programming Language :: Python :: 3
